{
  "generatedAt": "2025-12-08T18:17:45.278Z",
  "manufacturer": "FORD AUSTRALIA",
  "countGroups": 46,
  "groups": [
    {
      "manufacturerId": 1496,
      "manufacturerName": "FORD AUSTRALIA",
      "groupKey": "ANGLIA",
      "displayName": "ANGLIA",
      "confidence": "rule",
      "models": [
        {
          "modelId": 8485,
          "modelName": "ANGLIA A trois volumes (105E)",
          "modelYearFrom": "1960-03-01",
          "modelYearTo": "1965-06-01"
        },
        {
          "modelId": 90095,
          "modelName": "ANGLIA A trois volumes (E04A)",
          "modelYearFrom": "1939-10-01",
          "modelYearTo": "1947-12-01"
        },
        {
          "modelId": 90096,
          "modelName": "ANGLIA Décapotable (E04A)",
          "modelYearFrom": "1939-10-01",
          "modelYearTo": "1947-12-01"
        },
        {
          "modelId": 90097,
          "modelName": "ANGLIA A trois volumes (E54A)",
          "modelYearFrom": "1945-10-01",
          "modelYearTo": "1948-12-01"
        },
        {
          "modelId": 90098,
          "modelName": "ANGLIA Décapotable (E54A)",
          "modelYearFrom": "1945-10-01",
          "modelYearTo": "1948-12-01"
        },
        {
          "modelId": 90099,
          "modelName": "ANGLIA Coupe Utility (E54A)",
          "modelYearFrom": "1945-10-01",
          "modelYearTo": "1948-12-01"
        },
        {
          "modelId": 90100,
          "modelName": "ANGLIA Panel Van (E54A)",
          "modelYearFrom": "1945-10-01",
          "modelYearTo": "1948-12-01"
        },
        {
          "modelId": 90101,
          "modelName": "ANGLIA A trois volumes (E494A)",
          "modelYearFrom": "1949-01-01",
          "modelYearTo": "1952-12-01"
        },
        {
          "modelId": 90102,
          "modelName": "ANGLIA Décapotable (E494A)",
          "modelYearFrom": "1949-01-01",
          "modelYearTo": "1952-12-01"
        },
        {
          "modelId": 90103,
          "modelName": "ANGLIA Coupe Utility (E494A)",
          "modelYearFrom": "1949-01-01",
          "modelYearTo": "1952-12-01"
        },
        {
          "modelId": 90104,
          "modelName": "ANGLIA Panel Van (E494A)",
          "modelYearFrom": "1949-01-01",
          "modelYearTo": "1952-12-01"
        },
        {
          "modelId": 90105,
          "modelName": "ANGLIA A trois volumes (100E)",
          "modelYearFrom": "1953-01-01",
          "modelYearTo": "1959-09-01"
        }
      ]
    },
    {
      "manufacturerId": 1496,
      "manufacturerName": "FORD AUSTRALIA",
      "groupKey": "BRONCO",
      "displayName": "BRONCO",
      "confidence": "rule",
      "models": [
        {
          "modelId": 8379,
          "modelName": "BRONCO",
          "modelYearFrom": "1981-02-01",
          "modelYearTo": "1987-12-01"
        }
      ]
    },
    {
      "manufacturerId": 1496,
      "manufacturerName": "FORD AUSTRALIA",
      "groupKey": "CAPRI",
      "displayName": "CAPRI",
      "confidence": "rule",
      "models": [
        {
          "modelId": 8237,
          "modelName": "CAPRI Coupé",
          "modelYearFrom": "1968-12-01",
          "modelYearTo": "1974-03-01"
        },
        {
          "modelId": 8240,
          "modelName": "CAPRI Décapotable (SA, SB, SC, SE)",
          "modelYearFrom": "1989-09-01",
          "modelYearTo": "1994-07-01"
        }
      ]
    },
    {
      "manufacturerId": 1496,
      "manufacturerName": "FORD AUSTRALIA",
      "groupKey": "CONSUL",
      "displayName": "CONSUL",
      "confidence": "rule",
      "models": [
        {
          "modelId": 40527,
          "modelName": "CONSUL MK 2 A trois volumes",
          "modelYearFrom": "1956-01-01",
          "modelYearTo": "1962-12-01"
        },
        {
          "modelId": 40528,
          "modelName": "CONSUL MK 2 Break",
          "modelYearFrom": "1959-01-01",
          "modelYearTo": "1962-12-01"
        },
        {
          "modelId": 40529,
          "modelName": "CONSUL MK 2 Décapotable",
          "modelYearFrom": "1956-01-01",
          "modelYearTo": "1962-12-01"
        },
        {
          "modelId": 40530,
          "modelName": "CONSUL MK 2 Pick-up",
          "modelYearFrom": "1956-01-01",
          "modelYearTo": "1962-12-01"
        }
      ]
    },
    {
      "manufacturerId": 1496,
      "manufacturerName": "FORD AUSTRALIA",
      "groupKey": "CORSAIR",
      "displayName": "CORSAIR",
      "confidence": "rule",
      "models": [
        {
          "modelId": 8241,
          "modelName": "CORSAIR A trois volumes (UA)",
          "modelYearFrom": "1989-10-01",
          "modelYearTo": "1992-12-01"
        },
        {
          "modelId": 8242,
          "modelName": "CORSAIR Berline bicorps trois ou cinq portes (UA)",
          "modelYearFrom": "1989-10-01",
          "modelYearTo": "1992-12-01"
        }
      ]
    },
    {
      "manufacturerId": 1496,
      "manufacturerName": "FORD AUSTRALIA",
      "groupKey": "CORTINA",
      "displayName": "CORTINA",
      "confidence": "rule",
      "models": [
        {
          "modelId": 7726,
          "modelName": "CORTINA A trois volumes (TC)",
          "modelYearFrom": "1971-01-01",
          "modelYearTo": "1974-09-01"
        },
        {
          "modelId": 7727,
          "modelName": "CORTINA A trois volumes (TD)",
          "modelYearFrom": "1974-10-01",
          "modelYearTo": "1977-05-01"
        },
        {
          "modelId": 7728,
          "modelName": "CORTINA Break (TD)",
          "modelYearFrom": "1974-10-01",
          "modelYearTo": "1977-05-01"
        },
        {
          "modelId": 7729,
          "modelName": "CORTINA A trois volumes (TE, TF)",
          "modelYearFrom": "1976-01-01",
          "modelYearTo": "1982-08-01"
        },
        {
          "modelId": 7730,
          "modelName": "CORTINA Break (TE, TF)",
          "modelYearFrom": "1977-06-01",
          "modelYearTo": "1982-08-01"
        },
        {
          "modelId": 8380,
          "modelName": "CORTINA Break (TC)",
          "modelYearFrom": "1971-01-01",
          "modelYearTo": "1974-09-01"
        },
        {
          "modelId": 40467,
          "modelName": "CORTINA MK 1 A trois volumes",
          "modelYearFrom": "1962-09-01",
          "modelYearTo": "1967-08-01"
        },
        {
          "modelId": 40468,
          "modelName": "CORTINA MK 1 Coupé",
          "modelYearFrom": "1962-09-01",
          "modelYearTo": "1967-08-01"
        },
        {
          "modelId": 40469,
          "modelName": "CORTINA MK 2 A trois volumes",
          "modelYearFrom": "1967-08-01",
          "modelYearTo": "1971-08-01"
        },
        {
          "modelId": 40470,
          "modelName": "CORTINA MK 2 Coupé",
          "modelYearFrom": "1967-08-01",
          "modelYearTo": "1971-08-01"
        }
      ]
    },
    {
      "manufacturerId": 1496,
      "manufacturerName": "FORD AUSTRALIA",
      "groupKey": "COUGAR",
      "displayName": "COUGAR",
      "confidence": "rule",
      "models": [
        {
          "modelId": 8200,
          "modelName": "COUGAR Coupé (SW, SX)",
          "modelYearFrom": "1999-10-01",
          "modelYearTo": "2003-03-01"
        }
      ]
    },
    {
      "manufacturerId": 1496,
      "manufacturerName": "FORD AUSTRALIA",
      "groupKey": "COURIER",
      "displayName": "COURIER",
      "confidence": "rule",
      "models": [
        {
          "modelId": 8359,
          "modelName": "COURIER Pick-up (PH)",
          "modelYearFrom": "2004-08-01",
          "modelYearTo": "2006-12-01"
        },
        {
          "modelId": 8360,
          "modelName": "COURIER Pick-up (PD)",
          "modelYearFrom": "1996-05-01",
          "modelYearTo": "1999-02-01"
        },
        {
          "modelId": 8361,
          "modelName": "COURIER Pick-up (PG)",
          "modelYearFrom": "2002-11-01",
          "modelYearTo": "2004-07-01"
        },
        {
          "modelId": 8362,
          "modelName": "COURIER Pick-up (PE)",
          "modelYearFrom": "1999-02-01",
          "modelYearTo": "2002-11-01"
        },
        {
          "modelId": 8363,
          "modelName": "COURIER Pick-up (PC)",
          "modelYearFrom": "1982-11-01",
          "modelYearTo": "1996-04-01"
        },
        {
          "modelId": 8386,
          "modelName": "COURIER Camion plate-forme/Châssis (PC)",
          "modelYearFrom": "1988-01-01",
          "modelYearTo": "1996-04-01"
        },
        {
          "modelId": 8394,
          "modelName": "COURIER Camion plate-forme/Châssis (PD)",
          "modelYearFrom": "1996-05-01",
          "modelYearTo": "1999-02-01"
        },
        {
          "modelId": 8395,
          "modelName": "COURIER Camion plate-forme/Châssis (PE)",
          "modelYearFrom": "1999-02-01",
          "modelYearTo": "2002-11-01"
        },
        {
          "modelId": 8396,
          "modelName": "COURIER Camion plate-forme/Châssis (PG)",
          "modelYearFrom": "2002-11-01",
          "modelYearTo": "2004-07-01"
        },
        {
          "modelId": 8398,
          "modelName": "COURIER Camion plate-forme/Châssis (PH)",
          "modelYearFrom": "2004-08-01",
          "modelYearTo": null
        },
        {
          "modelId": 8491,
          "modelName": "COURIER Pick-up",
          "modelYearFrom": "1978-11-01",
          "modelYearTo": "1985-12-01"
        }
      ]
    },
    {
      "manufacturerId": 1496,
      "manufacturerName": "FORD AUSTRALIA",
      "groupKey": "ECONOVAN",
      "displayName": "ECONOVAN",
      "confidence": "rule",
      "models": [
        {
          "modelId": 8383,
          "modelName": "ECONOVAN Fourgon (JH)",
          "modelYearFrom": "2000-01-01",
          "modelYearTo": "2006-07-01"
        },
        {
          "modelId": 8384,
          "modelName": "ECONOVAN Fourgon (JG)",
          "modelYearFrom": "1997-06-01",
          "modelYearTo": "2000-01-01"
        },
        {
          "modelId": 8385,
          "modelName": "ECONOVAN Camion plate-forme/Châssis (JG)",
          "modelYearFrom": "1997-06-01",
          "modelYearTo": "2000-01-01"
        },
        {
          "modelId": 8489,
          "modelName": "ECONOVAN Fourgon",
          "modelYearFrom": "1979-06-01",
          "modelYearTo": "1997-05-01"
        },
        {
          "modelId": 8490,
          "modelName": "ECONOVAN Camion plate-forme/Châssis",
          "modelYearFrom": "1985-04-01",
          "modelYearTo": "1997-05-01"
        }
      ]
    },
    {
      "manufacturerId": 1496,
      "manufacturerName": "FORD AUSTRALIA",
      "groupKey": "ECOSPORT",
      "displayName": "ECOSPORT",
      "confidence": "rule",
      "models": [
        {
          "modelId": 11894,
          "modelName": "ECOSPORT (BK, BL)",
          "modelYearFrom": "2013-12-01",
          "modelYearTo": null
        }
      ]
    },
    {
      "manufacturerId": 1496,
      "manufacturerName": "FORD AUSTRALIA",
      "groupKey": "ENDURA",
      "displayName": "ENDURA",
      "confidence": "rule",
      "models": [
        {
          "modelId": 39396,
          "modelName": "ENDURA (CA)",
          "modelYearFrom": "2018-10-01",
          "modelYearTo": null
        }
      ]
    },
    {
      "manufacturerId": 1496,
      "manufacturerName": "FORD AUSTRALIA",
      "groupKey": "ESCAPE",
      "displayName": "ESCAPE",
      "confidence": "rule",
      "models": [
        {
          "modelId": 8206,
          "modelName": "ESCAPE (BA, ZA, ZB, ZC, ZD)",
          "modelYearFrom": "2001-03-01",
          "modelYearTo": null
        },
        {
          "modelId": 37902,
          "modelName": "ESCAPE (ZG)",
          "modelYearFrom": "2016-09-01",
          "modelYearTo": null
        },
        {
          "modelId": 41344,
          "modelName": "ESCAPE III (ZH)",
          "modelYearFrom": "2020-04-01",
          "modelYearTo": null
        }
      ]
    },
    {
      "manufacturerId": 1496,
      "manufacturerName": "FORD AUSTRALIA",
      "groupKey": "ESCORT",
      "displayName": "ESCORT",
      "confidence": "rule",
      "models": [
        {
          "modelId": 8234,
          "modelName": "ESCORT A trois volumes",
          "modelYearFrom": "1968-01-01",
          "modelYearTo": "1976-02-01"
        },
        {
          "modelId": 8235,
          "modelName": "ESCORT A trois volumes",
          "modelYearFrom": "1974-12-01",
          "modelYearTo": "1980-08-01"
        },
        {
          "modelId": 8382,
          "modelName": "ESCORT Panel Van",
          "modelYearFrom": "1970-01-01",
          "modelYearTo": "1980-08-01"
        }
      ]
    },
    {
      "manufacturerId": 1496,
      "manufacturerName": "FORD AUSTRALIA",
      "groupKey": "EVEREST",
      "displayName": "EVEREST",
      "confidence": "rule",
      "models": [
        {
          "modelId": 14809,
          "modelName": "EVEREST I SUV (UA, UA II)",
          "modelYearFrom": "2015-07-01",
          "modelYearTo": "2022-05-01"
        },
        {
          "modelId": 43078,
          "modelName": "EVEREST II SUV (UB)",
          "modelYearFrom": "2022-06-01",
          "modelYearTo": null
        }
      ]
    },
    {
      "manufacturerId": 1496,
      "manufacturerName": "FORD AUSTRALIA",
      "groupKey": "EXPLORER",
      "displayName": "EXPLORER",
      "confidence": "rule",
      "models": [
        {
          "modelId": 8193,
          "modelName": "EXPLORER (U_)",
          "modelYearFrom": "1996-09-01",
          "modelYearTo": "2008-01-01"
        }
      ]
    },
    {
      "manufacturerId": 1496,
      "manufacturerName": "FORD AUSTRALIA",
      "groupKey": "F",
      "displayName": "F",
      "confidence": "rule",
      "models": [
        {
          "modelId": 8219,
          "modelName": "F-150 Pick-up",
          "modelYearFrom": "1991-10-01",
          "modelYearTo": "1996-09-01"
        },
        {
          "modelId": 8220,
          "modelName": "F-150 Pick-up",
          "modelYearFrom": "1996-10-01",
          "modelYearTo": "2003-11-01"
        },
        {
          "modelId": 8221,
          "modelName": "F-150 Pick-up",
          "modelYearFrom": "2003-10-01",
          "modelYearTo": "2007-09-01"
        },
        {
          "modelId": 8222,
          "modelName": "F-250 Pick-up",
          "modelYearFrom": "1982-10-01",
          "modelYearTo": "1986-08-01"
        },
        {
          "modelId": 8223,
          "modelName": "F-250 Pick-up",
          "modelYearFrom": "1986-09-01",
          "modelYearTo": "1991-09-01"
        },
        {
          "modelId": 8224,
          "modelName": "F-250 Pick-up",
          "modelYearFrom": "1991-10-01",
          "modelYearTo": "1997-04-01"
        },
        {
          "modelId": 8225,
          "modelName": "F-350 Pick-up",
          "modelYearFrom": "1988-10-01",
          "modelYearTo": "1997-04-01"
        },
        {
          "modelId": 8226,
          "modelName": "F-150 Pick-up",
          "modelYearFrom": "1986-09-01",
          "modelYearTo": "1991-08-01"
        },
        {
          "modelId": 8227,
          "modelName": "F-150 Pick-up",
          "modelYearFrom": "2007-10-01",
          "modelYearTo": null
        },
        {
          "modelId": 8228,
          "modelName": "F-250 Pick-up",
          "modelYearFrom": "1996-10-01",
          "modelYearTo": "2003-11-01"
        },
        {
          "modelId": 8229,
          "modelName": "F-250 Pick-up",
          "modelYearFrom": "2001-07-01",
          "modelYearTo": "2007-09-01"
        },
        {
          "modelId": 8230,
          "modelName": "F-250 Pick-up",
          "modelYearFrom": "2007-10-01",
          "modelYearTo": null
        },
        {
          "modelId": 8231,
          "modelName": "F-350 Pick-up",
          "modelYearFrom": "1996-10-01",
          "modelYearTo": "2003-11-01"
        },
        {
          "modelId": 8232,
          "modelName": "F-350 Pick-up",
          "modelYearFrom": "2003-10-01",
          "modelYearTo": "2007-09-01"
        },
        {
          "modelId": 8233,
          "modelName": "F-350 Pick-up",
          "modelYearFrom": "2007-10-01",
          "modelYearTo": null
        }
      ]
    },
    {
      "manufacturerId": 1496,
      "manufacturerName": "FORD AUSTRALIA",
      "groupKey": "FAIRLANE",
      "displayName": "FAIRLANE",
      "confidence": "rule",
      "models": [
        {
          "modelId": 7731,
          "modelName": "FAIRLANE A trois volumes (AU)",
          "modelYearFrom": "1999-03-01",
          "modelYearTo": "2002-12-01"
        },
        {
          "modelId": 7732,
          "modelName": "FAIRLANE A trois volumes (BA)",
          "modelYearFrom": "2003-07-01",
          "modelYearTo": "2005-09-01"
        },
        {
          "modelId": 7733,
          "modelName": "FAIRLANE A trois volumes (BF)",
          "modelYearFrom": "2005-10-01",
          "modelYearTo": null
        },
        {
          "modelId": 7734,
          "modelName": "FAIRLANE A trois volumes (NA)",
          "modelYearFrom": "1988-06-01",
          "modelYearTo": "1991-06-01"
        },
        {
          "modelId": 7735,
          "modelName": "FAIRLANE A trois volumes (NC)",
          "modelYearFrom": "1991-07-01",
          "modelYearTo": "1995-03-01"
        },
        {
          "modelId": 7736,
          "modelName": "FAIRLANE A trois volumes (NF)",
          "modelYearFrom": "1995-03-01",
          "modelYearTo": "1996-09-01"
        },
        {
          "modelId": 7737,
          "modelName": "FAIRLANE A trois volumes (NL)",
          "modelYearFrom": "1996-09-01",
          "modelYearTo": "1999-02-01"
        },
        {
          "modelId": 7738,
          "modelName": "FAIRLANE A trois volumes (ZA)",
          "modelYearFrom": "1967-03-01",
          "modelYearTo": "1968-02-01"
        },
        {
          "modelId": 7739,
          "modelName": "FAIRLANE A trois volumes (ZB)",
          "modelYearFrom": "1968-03-01",
          "modelYearTo": "1969-06-01"
        },
        {
          "modelId": 7740,
          "modelName": "FAIRLANE A trois volumes (ZC)",
          "modelYearFrom": "1969-07-01",
          "modelYearTo": "1970-10-01"
        },
        {
          "modelId": 7741,
          "modelName": "FAIRLANE A trois volumes (ZD)",
          "modelYearFrom": "1970-11-01",
          "modelYearTo": "1972-03-01"
        },
        {
          "modelId": 7742,
          "modelName": "FAIRLANE A trois volumes (ZF)",
          "modelYearFrom": "1972-04-01",
          "modelYearTo": "1973-10-01"
        },
        {
          "modelId": 7743,
          "modelName": "FAIRLANE A trois volumes (ZG)",
          "modelYearFrom": "1973-11-01",
          "modelYearTo": "1976-05-01"
        },
        {
          "modelId": 7744,
          "modelName": "FAIRLANE A trois volumes (ZH)",
          "modelYearFrom": "1976-05-01",
          "modelYearTo": "1979-04-01"
        },
        {
          "modelId": 7745,
          "modelName": "FAIRLANE A trois volumes (ZJ)",
          "modelYearFrom": "1979-05-01",
          "modelYearTo": "1982-03-01"
        },
        {
          "modelId": 7746,
          "modelName": "FAIRLANE A trois volumes (ZK)",
          "modelYearFrom": "1982-03-01",
          "modelYearTo": "1984-09-01"
        },
        {
          "modelId": 7747,
          "modelName": "FAIRLANE A trois volumes (ZL)",
          "modelYearFrom": "1984-10-01",
          "modelYearTo": "1988-05-01"
        },
        {
          "modelId": 37985,
          "modelName": "FAIRLANE A trois volumes (FB, FC)",
          "modelYearFrom": "1962-05-01",
          "modelYearTo": "1964-12-01"
        },
        {
          "modelId": 37986,
          "modelName": "FAIRLANE Break (FC)",
          "modelYearFrom": "1963-01-01",
          "modelYearTo": "1964-12-01"
        },
        {
          "modelId": 45069,
          "modelName": "FAIRLANE A trois volumes",
          "modelYearFrom": "1959-09-01",
          "modelYearTo": "1962-04-01"
        },
        {
          "modelId": 45070,
          "modelName": "FAIRLANE A trois volumes (FD)",
          "modelYearFrom": "1964-04-01",
          "modelYearTo": "1965-12-01"
        },
        {
          "modelId": 90050,
          "modelName": "FAIRLANE",
          "modelYearFrom": "1959-09-01",
          "modelYearTo": "1962-04-01"
        }
      ]
    },
    {
      "manufacturerId": 1496,
      "manufacturerName": "FORD AUSTRALIA",
      "groupKey": "FAIRMONT",
      "displayName": "FAIRMONT",
      "confidence": "rule",
      "models": [
        {
          "modelId": 8401,
          "modelName": "FAIRMONT A trois volumes (AU)",
          "modelYearFrom": "1998-09-01",
          "modelYearTo": "2002-09-01"
        },
        {
          "modelId": 8402,
          "modelName": "FAIRMONT A trois volumes (BA)",
          "modelYearFrom": "2002-09-01",
          "modelYearTo": "2005-09-01"
        },
        {
          "modelId": 8403,
          "modelName": "FAIRMONT A trois volumes (BF)",
          "modelYearFrom": "2005-10-01",
          "modelYearTo": "2008-04-01"
        },
        {
          "modelId": 8404,
          "modelName": "FAIRMONT A trois volumes (EA)",
          "modelYearFrom": "1988-03-01",
          "modelYearTo": "1991-06-01"
        },
        {
          "modelId": 8405,
          "modelName": "FAIRMONT A trois volumes (EB)",
          "modelYearFrom": "1991-07-01",
          "modelYearTo": "1993-08-01"
        },
        {
          "modelId": 8406,
          "modelName": "FAIRMONT Break (EB)",
          "modelYearFrom": "1991-07-01",
          "modelYearTo": "1993-08-01"
        },
        {
          "modelId": 8407,
          "modelName": "FAIRMONT A trois volumes (ED)",
          "modelYearFrom": "1993-08-01",
          "modelYearTo": "1994-08-01"
        },
        {
          "modelId": 8408,
          "modelName": "FAIRMONT A trois volumes (EF)",
          "modelYearFrom": "1994-08-01",
          "modelYearTo": "1996-09-01"
        },
        {
          "modelId": 8409,
          "modelName": "FAIRMONT Break (EL)",
          "modelYearFrom": "1996-09-01",
          "modelYearTo": "1998-08-01"
        },
        {
          "modelId": 8413,
          "modelName": "FAIRMONT A trois volumes (XD)",
          "modelYearFrom": "1979-03-01",
          "modelYearTo": "1982-02-01"
        },
        {
          "modelId": 8415,
          "modelName": "FAIRMONT Break (XD)",
          "modelYearFrom": "1979-03-01",
          "modelYearTo": "1982-02-01"
        },
        {
          "modelId": 8418,
          "modelName": "FAIRMONT Break (XE)",
          "modelYearFrom": "1982-03-01",
          "modelYearTo": "1984-09-01"
        },
        {
          "modelId": 8419,
          "modelName": "FAIRMONT A trois volumes (XE)",
          "modelYearFrom": "1982-03-01",
          "modelYearTo": "1984-09-01"
        },
        {
          "modelId": 8424,
          "modelName": "FAIRMONT A trois volumes (XF)",
          "modelYearFrom": "1984-10-01",
          "modelYearTo": "1988-02-01"
        },
        {
          "modelId": 9031,
          "modelName": "FAIRMONT Break (AU)",
          "modelYearFrom": "1998-09-01",
          "modelYearTo": "2002-09-01"
        },
        {
          "modelId": 9032,
          "modelName": "FAIRMONT Break (EF)",
          "modelYearFrom": "1994-08-01",
          "modelYearTo": "1996-09-01"
        },
        {
          "modelId": 9033,
          "modelName": "FAIRMONT Break (ED)",
          "modelYearFrom": "1993-08-01",
          "modelYearTo": "1994-08-01"
        },
        {
          "modelId": 9034,
          "modelName": "FAIRMONT A trois volumes (EL)",
          "modelYearFrom": "1996-09-01",
          "modelYearTo": "1998-08-01"
        },
        {
          "modelId": 9074,
          "modelName": "FAIRMONT Break (EA)",
          "modelYearFrom": "1988-03-01",
          "modelYearTo": "1991-06-01"
        },
        {
          "modelId": 37994,
          "modelName": "FAIRMONT Break (XR)",
          "modelYearFrom": "1966-01-01",
          "modelYearTo": "1968-12-01"
        },
        {
          "modelId": 37995,
          "modelName": "FAIRMONT Break (XT)",
          "modelYearFrom": "1968-03-01",
          "modelYearTo": "1969-08-01"
        },
        {
          "modelId": 37996,
          "modelName": "FAIRMONT Break (XW)",
          "modelYearFrom": "1969-09-01",
          "modelYearTo": "1970-10-01"
        },
        {
          "modelId": 37997,
          "modelName": "FAIRMONT Break (XY)",
          "modelYearFrom": "1970-01-01",
          "modelYearTo": "1972-02-01"
        },
        {
          "modelId": 37998,
          "modelName": "FAIRMONT Break (XP)",
          "modelYearFrom": "1965-06-01",
          "modelYearTo": "1966-02-01"
        },
        {
          "modelId": 37999,
          "modelName": "FAIRMONT A trois volumes (XY)",
          "modelYearFrom": "1970-01-01",
          "modelYearTo": "1972-09-01"
        },
        {
          "modelId": 38000,
          "modelName": "FAIRMONT A trois volumes (XT)",
          "modelYearFrom": "1968-03-01",
          "modelYearTo": "1969-08-01"
        },
        {
          "modelId": 38001,
          "modelName": "FAIRMONT A trois volumes (XW)",
          "modelYearFrom": "1969-09-01",
          "modelYearTo": "1970-10-01"
        },
        {
          "modelId": 38003,
          "modelName": "FAIRMONT A trois volumes (XP)",
          "modelYearFrom": "1965-06-01",
          "modelYearTo": "1966-02-01"
        },
        {
          "modelId": 38004,
          "modelName": "FAIRMONT A trois volumes (XR)",
          "modelYearFrom": "1967-03-01",
          "modelYearTo": "1968-03-01"
        },
        {
          "modelId": 38018,
          "modelName": "FAIRMONT Break (XF)",
          "modelYearFrom": "1984-10-01",
          "modelYearTo": "1988-01-01"
        },
        {
          "modelId": 43094,
          "modelName": "FAIRMONT A trois volumes (XA)",
          "modelYearFrom": "1972-03-01",
          "modelYearTo": "1973-09-01"
        },
        {
          "modelId": 43095,
          "modelName": "FAIRMONT Break (XA)",
          "modelYearFrom": "1972-03-01",
          "modelYearTo": "1973-09-01"
        },
        {
          "modelId": 43096,
          "modelName": "FAIRMONT Coupé (XA)",
          "modelYearFrom": "1972-03-01",
          "modelYearTo": "1973-09-01"
        },
        {
          "modelId": 43099,
          "modelName": "FAIRMONT A trois volumes (XB)",
          "modelYearFrom": "1973-10-01",
          "modelYearTo": "1976-08-01"
        },
        {
          "modelId": 43100,
          "modelName": "FAIRMONT Break (XB)",
          "modelYearFrom": "1973-10-01",
          "modelYearTo": "1976-08-01"
        },
        {
          "modelId": 43101,
          "modelName": "FAIRMONT Coupé (XB)",
          "modelYearFrom": "1973-10-01",
          "modelYearTo": "1976-08-01"
        },
        {
          "modelId": 43104,
          "modelName": "FAIRMONT A trois volumes (XC)",
          "modelYearFrom": "1976-08-01",
          "modelYearTo": "1979-03-01"
        },
        {
          "modelId": 43105,
          "modelName": "FAIRMONT Break (XC)",
          "modelYearFrom": "1976-08-01",
          "modelYearTo": "1979-03-01"
        },
        {
          "modelId": 43106,
          "modelName": "FAIRMONT Coupé (XC)",
          "modelYearFrom": "1976-08-01",
          "modelYearTo": "1979-03-01"
        }
      ]
    },
    {
      "manufacturerId": 1496,
      "manufacturerName": "FORD AUSTRALIA",
      "groupKey": "FALCON",
      "displayName": "FALCON",
      "confidence": "rule",
      "models": [
        {
          "modelId": 7748,
          "modelName": "FALCON A trois volumes (AU)",
          "modelYearFrom": "1998-08-01",
          "modelYearTo": "2002-09-01"
        },
        {
          "modelId": 7749,
          "modelName": "FALCON Pick-up (AU)",
          "modelYearFrom": "1998-09-01",
          "modelYearTo": "2002-09-01"
        },
        {
          "modelId": 7750,
          "modelName": "FALCON Break (AU)",
          "modelYearFrom": "1998-08-01",
          "modelYearTo": "2002-09-01"
        },
        {
          "modelId": 7751,
          "modelName": "FALCON A trois volumes (BA)",
          "modelYearFrom": "2002-09-01",
          "modelYearTo": "2005-09-01"
        },
        {
          "modelId": 7752,
          "modelName": "FALCON Pick-up (BA)",
          "modelYearFrom": "2002-09-01",
          "modelYearTo": "2005-09-01"
        },
        {
          "modelId": 7753,
          "modelName": "FALCON Break (BA)",
          "modelYearFrom": "2002-09-01",
          "modelYearTo": "2005-09-01"
        },
        {
          "modelId": 7754,
          "modelName": "FALCON A trois volumes (BF)",
          "modelYearFrom": "2005-10-01",
          "modelYearTo": "2008-04-01"
        },
        {
          "modelId": 7755,
          "modelName": "FALCON Pick-up (BF)",
          "modelYearFrom": "2005-10-01",
          "modelYearTo": null
        },
        {
          "modelId": 7756,
          "modelName": "FALCON Break (BF)",
          "modelYearFrom": "2005-10-01",
          "modelYearTo": "2010-05-01"
        },
        {
          "modelId": 7757,
          "modelName": "FALCON A trois volumes (EA)",
          "modelYearFrom": "1988-03-01",
          "modelYearTo": "1991-06-01"
        },
        {
          "modelId": 7758,
          "modelName": "FALCON Break (EA)",
          "modelYearFrom": "1988-03-01",
          "modelYearTo": "1991-06-01"
        },
        {
          "modelId": 7759,
          "modelName": "FALCON A trois volumes (EB)",
          "modelYearFrom": "1991-07-01",
          "modelYearTo": "1993-08-01"
        },
        {
          "modelId": 7760,
          "modelName": "FALCON Break (EB)",
          "modelYearFrom": "1991-07-01",
          "modelYearTo": "1993-08-01"
        },
        {
          "modelId": 7761,
          "modelName": "FALCON A trois volumes (ED)",
          "modelYearFrom": "1993-08-01",
          "modelYearTo": "1994-08-01"
        },
        {
          "modelId": 7762,
          "modelName": "FALCON Break (ED)",
          "modelYearFrom": "1993-08-01",
          "modelYearTo": "1994-08-01"
        },
        {
          "modelId": 7763,
          "modelName": "FALCON A trois volumes (EF)",
          "modelYearFrom": "1994-08-01",
          "modelYearTo": "1996-09-01"
        },
        {
          "modelId": 7764,
          "modelName": "FALCON Break (EF)",
          "modelYearFrom": "1994-08-01",
          "modelYearTo": "1996-09-01"
        },
        {
          "modelId": 7765,
          "modelName": "FALCON A trois volumes (EL)",
          "modelYearFrom": "1996-09-01",
          "modelYearTo": "1998-08-01"
        },
        {
          "modelId": 7766,
          "modelName": "FALCON Break (EL)",
          "modelYearFrom": "1996-09-01",
          "modelYearTo": "1998-08-01"
        },
        {
          "modelId": 7769,
          "modelName": "FALCON A trois volumes (XD)",
          "modelYearFrom": "1979-03-01",
          "modelYearTo": "1982-02-01"
        },
        {
          "modelId": 7770,
          "modelName": "FALCON Pick-up (XD)",
          "modelYearFrom": "1979-03-01",
          "modelYearTo": "1982-03-01"
        },
        {
          "modelId": 7771,
          "modelName": "FALCON Break (XD)",
          "modelYearFrom": "1979-03-01",
          "modelYearTo": "1982-02-01"
        },
        {
          "modelId": 7772,
          "modelName": "FALCON A trois volumes (XE)",
          "modelYearFrom": "1982-03-01",
          "modelYearTo": "1984-09-01"
        },
        {
          "modelId": 7773,
          "modelName": "FALCON Pick-up (XE)",
          "modelYearFrom": "1982-03-01",
          "modelYearTo": "1984-10-01"
        },
        {
          "modelId": 7774,
          "modelName": "FALCON Break (XE)",
          "modelYearFrom": "1982-03-01",
          "modelYearTo": "1984-09-01"
        },
        {
          "modelId": 7775,
          "modelName": "FALCON A trois volumes (XF)",
          "modelYearFrom": "1984-10-01",
          "modelYearTo": "1988-02-01"
        },
        {
          "modelId": 7776,
          "modelName": "FALCON Pick-up (XF)",
          "modelYearFrom": "1984-10-01",
          "modelYearTo": "1993-03-01"
        },
        {
          "modelId": 7777,
          "modelName": "FALCON Panel Van (XF)",
          "modelYearFrom": "1984-10-01",
          "modelYearTo": "1993-03-01"
        },
        {
          "modelId": 7778,
          "modelName": "FALCON Break (XF)",
          "modelYearFrom": "1984-10-01",
          "modelYearTo": "1988-02-01"
        },
        {
          "modelId": 7779,
          "modelName": "FALCON Pick-up (XG)",
          "modelYearFrom": "1993-03-01",
          "modelYearTo": "1996-03-01"
        },
        {
          "modelId": 7780,
          "modelName": "FALCON Panel Van (XG)",
          "modelYearFrom": "1993-03-01",
          "modelYearTo": "1996-03-01"
        },
        {
          "modelId": 7781,
          "modelName": "FALCON Pick-up (XH)",
          "modelYearFrom": "1996-03-01",
          "modelYearTo": "1999-05-01"
        },
        {
          "modelId": 7782,
          "modelName": "FALCON A trois volumes (XK)",
          "modelYearFrom": "1960-01-01",
          "modelYearTo": "1961-01-01"
        },
        {
          "modelId": 7783,
          "modelName": "FALCON A trois volumes (XL)",
          "modelYearFrom": "1961-01-01",
          "modelYearTo": "1963-12-01"
        },
        {
          "modelId": 7784,
          "modelName": "FALCON A trois volumes (XM)",
          "modelYearFrom": "1964-01-01",
          "modelYearTo": "1965-01-01"
        },
        {
          "modelId": 7785,
          "modelName": "FALCON A trois volumes (XP)",
          "modelYearFrom": "1965-01-01",
          "modelYearTo": "1966-08-01"
        },
        {
          "modelId": 7786,
          "modelName": "FALCON A trois volumes (XR)",
          "modelYearFrom": "1966-09-01",
          "modelYearTo": "1968-02-01"
        },
        {
          "modelId": 7787,
          "modelName": "FALCON A trois volumes (XT)",
          "modelYearFrom": "1968-03-01",
          "modelYearTo": "1969-05-01"
        },
        {
          "modelId": 7788,
          "modelName": "FALCON A trois volumes (XW)",
          "modelYearFrom": "1969-06-01",
          "modelYearTo": "1971-07-01"
        },
        {
          "modelId": 7789,
          "modelName": "FALCON A trois volumes (XY)",
          "modelYearFrom": "1970-11-01",
          "modelYearTo": "1972-03-01"
        },
        {
          "modelId": 8265,
          "modelName": "FALCON A trois volumes (FG)",
          "modelYearFrom": "2008-02-01",
          "modelYearTo": "2014-12-01"
        },
        {
          "modelId": 8425,
          "modelName": "FALCON Camion plate-forme/Châssis (AU)",
          "modelYearFrom": "1999-07-01",
          "modelYearTo": "2002-09-01"
        },
        {
          "modelId": 8426,
          "modelName": "FALCON Camion plate-forme/Châssis (BA)",
          "modelYearFrom": "2002-09-01",
          "modelYearTo": "2005-09-01"
        },
        {
          "modelId": 8427,
          "modelName": "FALCON Camion plate-forme/Châssis (BF)",
          "modelYearFrom": "2005-10-01",
          "modelYearTo": "2008-04-01"
        },
        {
          "modelId": 8429,
          "modelName": "FALCON Pick-up (FG)",
          "modelYearFrom": "2008-02-01",
          "modelYearTo": "2014-12-01"
        },
        {
          "modelId": 8430,
          "modelName": "FALCON Camion plate-forme/Châssis (FG)",
          "modelYearFrom": "2008-02-01",
          "modelYearTo": "2014-12-01"
        },
        {
          "modelId": 8431,
          "modelName": "FALCON Panel Van (XH)",
          "modelYearFrom": "1996-03-01",
          "modelYearTo": "1999-05-01"
        },
        {
          "modelId": 9030,
          "modelName": "FALCON Panel Van (XE)",
          "modelYearFrom": "1982-03-01",
          "modelYearTo": "1984-10-01"
        },
        {
          "modelId": 13858,
          "modelName": "FALCON Pick-up (FG X)",
          "modelYearFrom": "2014-11-01",
          "modelYearTo": null
        },
        {
          "modelId": 13860,
          "modelName": "FALCON Camion plate-forme/Châssis (FG X)",
          "modelYearFrom": "2014-11-01",
          "modelYearTo": null
        },
        {
          "modelId": 13861,
          "modelName": "FALCON A trois volumes (FG X)",
          "modelYearFrom": "2014-11-01",
          "modelYearTo": null
        },
        {
          "modelId": 14393,
          "modelName": "FALCON Break (XK)",
          "modelYearFrom": "1960-01-01",
          "modelYearTo": "1962-08-01"
        },
        {
          "modelId": 14528,
          "modelName": "FALCON Panel Van (XK)",
          "modelYearFrom": "1960-01-01",
          "modelYearTo": "1962-08-01"
        },
        {
          "modelId": 14529,
          "modelName": "FALCON Pick-up (XK)",
          "modelYearFrom": "1960-01-01",
          "modelYearTo": "1962-08-01"
        },
        {
          "modelId": 14530,
          "modelName": "FALCON Break (XL)",
          "modelYearFrom": "1962-09-01",
          "modelYearTo": "1963-12-01"
        },
        {
          "modelId": 14531,
          "modelName": "FALCON Panel Van (XL)",
          "modelYearFrom": "1961-01-01",
          "modelYearTo": "1963-12-01"
        },
        {
          "modelId": 14532,
          "modelName": "FALCON Pick-up (XL)",
          "modelYearFrom": "1962-09-01",
          "modelYearTo": "1963-12-01"
        },
        {
          "modelId": 14533,
          "modelName": "FALCON Break (XM)",
          "modelYearFrom": "1964-01-01",
          "modelYearTo": "1965-01-01"
        },
        {
          "modelId": 14534,
          "modelName": "FALCON Panel Van (XM)",
          "modelYearFrom": "1964-01-01",
          "modelYearTo": "1965-01-01"
        },
        {
          "modelId": 14535,
          "modelName": "FALCON Pick-up (XM)",
          "modelYearFrom": "1964-01-01",
          "modelYearTo": "1965-01-01"
        },
        {
          "modelId": 14536,
          "modelName": "FALCON Break (XP)",
          "modelYearFrom": "1965-01-01",
          "modelYearTo": "1966-08-01"
        },
        {
          "modelId": 14537,
          "modelName": "FALCON Panel Van (XP)",
          "modelYearFrom": "1965-01-01",
          "modelYearTo": "1966-08-01"
        },
        {
          "modelId": 14538,
          "modelName": "FALCON Pick-up (XP)",
          "modelYearFrom": "1965-01-01",
          "modelYearTo": "1966-08-01"
        },
        {
          "modelId": 38005,
          "modelName": "FALCON Break (XW)",
          "modelYearFrom": "1969-07-01",
          "modelYearTo": "1970-10-01"
        },
        {
          "modelId": 38006,
          "modelName": "FALCON Break (XR)",
          "modelYearFrom": "1966-09-01",
          "modelYearTo": "1968-03-01"
        },
        {
          "modelId": 38008,
          "modelName": "FALCON Panel Van (XT)",
          "modelYearFrom": "1968-04-01",
          "modelYearTo": "1969-06-01"
        },
        {
          "modelId": 38009,
          "modelName": "FALCON Panel Van (XR)",
          "modelYearFrom": "1966-09-01",
          "modelYearTo": "1968-03-01"
        },
        {
          "modelId": 38010,
          "modelName": "FALCON Pick-up (XW)",
          "modelYearFrom": "1969-07-01",
          "modelYearTo": "1970-10-01"
        },
        {
          "modelId": 38011,
          "modelName": "FALCON Pick-up (XY)",
          "modelYearFrom": "1970-11-01",
          "modelYearTo": "1972-03-01"
        },
        {
          "modelId": 38012,
          "modelName": "FALCON Pick-up (XR)",
          "modelYearFrom": "1966-09-01",
          "modelYearTo": "1968-03-01"
        },
        {
          "modelId": 38013,
          "modelName": "FALCON Pick-up (XT)",
          "modelYearFrom": "1968-04-01",
          "modelYearTo": "1969-06-01"
        },
        {
          "modelId": 38014,
          "modelName": "FALCON Break (XT)",
          "modelYearFrom": "1968-03-01",
          "modelYearTo": "1969-06-01"
        },
        {
          "modelId": 38017,
          "modelName": "FALCON Panel Van (XD)",
          "modelYearFrom": "1979-04-01",
          "modelYearTo": "1982-03-01"
        },
        {
          "modelId": 39834,
          "modelName": "FALCON Break (XY)",
          "modelYearFrom": "1970-11-01",
          "modelYearTo": "1972-03-01"
        },
        {
          "modelId": 39835,
          "modelName": "FALCON Coupé (XC)",
          "modelYearFrom": "1976-09-01",
          "modelYearTo": "1979-03-01"
        },
        {
          "modelId": 39836,
          "modelName": "FALCON Coupé (XA)",
          "modelYearFrom": "1972-03-01",
          "modelYearTo": "1973-09-01"
        },
        {
          "modelId": 39837,
          "modelName": "FALCON Coupé (XB)",
          "modelYearFrom": "1973-10-01",
          "modelYearTo": "1976-08-01"
        },
        {
          "modelId": 39838,
          "modelName": "FALCON Panel Van (XB)",
          "modelYearFrom": "1973-10-01",
          "modelYearTo": "1976-08-01"
        },
        {
          "modelId": 39839,
          "modelName": "FALCON Pick-up (XB)",
          "modelYearFrom": "1973-10-01",
          "modelYearTo": "1976-08-01"
        },
        {
          "modelId": 39840,
          "modelName": "FALCON Coupé (XM)",
          "modelYearFrom": "1964-01-01",
          "modelYearTo": "1965-01-01"
        },
        {
          "modelId": 39842,
          "modelName": "FALCON Coupé (XP)",
          "modelYearFrom": "1965-01-01",
          "modelYearTo": "1966-08-01"
        },
        {
          "modelId": 39843,
          "modelName": "FALCON Panel Van (XY)",
          "modelYearFrom": "1970-11-01",
          "modelYearTo": "1972-03-01"
        },
        {
          "modelId": 39844,
          "modelName": "FALCON Pick-up (XA)",
          "modelYearFrom": "1972-03-01",
          "modelYearTo": "1973-09-01"
        },
        {
          "modelId": 39845,
          "modelName": "FALCON Pick-up (XC)",
          "modelYearFrom": "1976-08-01",
          "modelYearTo": "1979-08-01"
        },
        {
          "modelId": 39846,
          "modelName": "FALCON Panel Van (XA)",
          "modelYearFrom": "1972-03-01",
          "modelYearTo": "1973-09-01"
        },
        {
          "modelId": 39847,
          "modelName": "FALCON Panel Van (XC)",
          "modelYearFrom": "1976-08-01",
          "modelYearTo": "1979-10-01"
        },
        {
          "modelId": 43092,
          "modelName": "FALCON A trois volumes (XA)",
          "modelYearFrom": "1972-03-01",
          "modelYearTo": "1973-09-01"
        },
        {
          "modelId": 43093,
          "modelName": "FALCON Break (XA)",
          "modelYearFrom": "1972-03-01",
          "modelYearTo": "1973-09-01"
        },
        {
          "modelId": 43097,
          "modelName": "FALCON A trois volumes (XB)",
          "modelYearFrom": "1973-10-01",
          "modelYearTo": "1976-08-01"
        },
        {
          "modelId": 43098,
          "modelName": "FALCON Break (XB)",
          "modelYearFrom": "1973-10-01",
          "modelYearTo": "1976-08-01"
        },
        {
          "modelId": 43102,
          "modelName": "FALCON A trois volumes (XC)",
          "modelYearFrom": "1976-08-01",
          "modelYearTo": "1979-03-01"
        },
        {
          "modelId": 43103,
          "modelName": "FALCON Break (XC)",
          "modelYearFrom": "1976-08-01",
          "modelYearTo": "1979-03-01"
        },
        {
          "modelId": 45071,
          "modelName": "FALCON Panel Van (XW)",
          "modelYearFrom": "1969-07-01",
          "modelYearTo": "1970-11-01"
        }
      ]
    },
    {
      "manufacturerId": 1496,
      "manufacturerName": "FORD AUSTRALIA",
      "groupKey": "FESTIVA",
      "displayName": "FESTIVA",
      "confidence": "rule",
      "models": [
        {
          "modelId": 8432,
          "modelName": "FESTIVA (WA)",
          "modelYearFrom": "1991-10-01",
          "modelYearTo": "1994-03-01"
        },
        {
          "modelId": 8434,
          "modelName": "FESTIVA (WB)",
          "modelYearFrom": "1994-04-01",
          "modelYearTo": "1997-12-01"
        },
        {
          "modelId": 8435,
          "modelName": "FESTIVA (WD)",
          "modelYearFrom": "1997-01-01",
          "modelYearTo": "1997-12-01"
        },
        {
          "modelId": 8436,
          "modelName": "FESTIVA (WF)",
          "modelYearFrom": "1998-01-01",
          "modelYearTo": "2001-12-01"
        }
      ]
    },
    {
      "manufacturerId": 1496,
      "manufacturerName": "FORD AUSTRALIA",
      "groupKey": "FIESTA",
      "displayName": "FIESTA",
      "confidence": "rule",
      "models": [
        {
          "modelId": 8210,
          "modelName": "FIESTA Berline bicorps trois ou cinq portes (WP, WQ)",
          "modelYearFrom": "2004-04-01",
          "modelYearTo": null
        },
        {
          "modelId": 8266,
          "modelName": "FIESTA Berline bicorps trois ou cinq portes (WS)",
          "modelYearFrom": "2008-10-01",
          "modelYearTo": null
        },
        {
          "modelId": 9569,
          "modelName": "FIESTA Berline bicorps trois ou cinq portes (WT)",
          "modelYearFrom": "2010-10-01",
          "modelYearTo": null
        },
        {
          "modelId": 9570,
          "modelName": "FIESTA A trois volumes (WT)",
          "modelYearFrom": "2010-10-01",
          "modelYearTo": null
        },
        {
          "modelId": 13234,
          "modelName": "FIESTA Berline bicorps trois ou cinq portes (WZ)",
          "modelYearFrom": "2013-05-01",
          "modelYearTo": null
        },
        {
          "modelId": 41799,
          "modelName": "FIESTA (WG)",
          "modelYearFrom": "2019-07-01",
          "modelYearTo": null
        }
      ]
    },
    {
      "manufacturerId": 1496,
      "manufacturerName": "FORD AUSTRALIA",
      "groupKey": "FOCUS",
      "displayName": "FOCUS",
      "confidence": "rule",
      "models": [
        {
          "modelId": 8201,
          "modelName": "FOCUS Berline bicorps trois ou cinq portes (LR)",
          "modelYearFrom": "2002-09-01",
          "modelYearTo": "2005-06-01"
        },
        {
          "modelId": 8202,
          "modelName": "FOCUS A trois volumes (LR)",
          "modelYearFrom": "2002-09-01",
          "modelYearTo": "2005-06-01"
        },
        {
          "modelId": 8212,
          "modelName": "FOCUS Berline bicorps trois ou cinq portes (LT)",
          "modelYearFrom": "2007-07-01",
          "modelYearTo": "2009-03-01"
        },
        {
          "modelId": 8213,
          "modelName": "FOCUS A trois volumes (LS, LT)",
          "modelYearFrom": "2005-05-01",
          "modelYearTo": null
        },
        {
          "modelId": 8437,
          "modelName": "FOCUS Berline bicorps trois ou cinq portes (LV)",
          "modelYearFrom": "2009-03-01",
          "modelYearTo": "2011-08-01"
        },
        {
          "modelId": 8438,
          "modelName": "FOCUS A trois volumes (LV)",
          "modelYearFrom": "2009-03-01",
          "modelYearTo": "2011-08-01"
        },
        {
          "modelId": 8496,
          "modelName": "FOCUS Décapotable (LT)",
          "modelYearFrom": "2007-12-01",
          "modelYearTo": "2009-03-01"
        },
        {
          "modelId": 9754,
          "modelName": "FOCUS Berline bicorps trois ou cinq portes (LW)",
          "modelYearFrom": "2011-08-01",
          "modelYearTo": null
        },
        {
          "modelId": 9755,
          "modelName": "FOCUS A trois volumes (LW)",
          "modelYearFrom": "2011-08-01",
          "modelYearTo": null
        },
        {
          "modelId": 14840,
          "modelName": "FOCUS Berline bicorps trois ou cinq portes (LZ)",
          "modelYearFrom": "2015-05-01",
          "modelYearTo": null
        },
        {
          "modelId": 14841,
          "modelName": "FOCUS A trois volumes (LZ)",
          "modelYearFrom": "2015-05-01",
          "modelYearTo": null
        },
        {
          "modelId": 39383,
          "modelName": "FOCUS Berline bicorps trois ou cinq portes (SA)",
          "modelYearFrom": "2018-08-01",
          "modelYearTo": null
        },
        {
          "modelId": 39384,
          "modelName": "FOCUS Break (SA)",
          "modelYearFrom": "2018-08-01",
          "modelYearTo": null
        },
        {
          "modelId": 39794,
          "modelName": "FOCUS Berline bicorps trois ou cinq portes (LS)",
          "modelYearFrom": "2005-06-01",
          "modelYearTo": "2007-06-01"
        },
        {
          "modelId": 45368,
          "modelName": "FOCUS Décapotable (LV)",
          "modelYearFrom": "2008-01-01",
          "modelYearTo": "2008-12-01"
        }
      ]
    },
    {
      "manufacturerId": 1496,
      "manufacturerName": "FORD AUSTRALIA",
      "groupKey": "GALAXIE",
      "displayName": "GALAXIE",
      "confidence": "rule",
      "models": [
        {
          "modelId": 45068,
          "modelName": "GALAXIE LTD A trois volumes",
          "modelYearFrom": "1969-10-01",
          "modelYearTo": "1973-12-01"
        },
        {
          "modelId": 45079,
          "modelName": "GALAXIE I A trois volumes",
          "modelYearFrom": "1958-10-01",
          "modelYearTo": "1959-09-01"
        },
        {
          "modelId": 45080,
          "modelName": "GALAXIE I Station Wagon",
          "modelYearFrom": "1958-10-01",
          "modelYearTo": "1959-09-01"
        },
        {
          "modelId": 45081,
          "modelName": "GALAXIE I Hardtop",
          "modelYearFrom": "1958-10-01",
          "modelYearTo": "1959-09-01"
        },
        {
          "modelId": 45082,
          "modelName": "GALAXIE I Décapotable",
          "modelYearFrom": "1958-10-01",
          "modelYearTo": "1959-09-01"
        },
        {
          "modelId": 45083,
          "modelName": "GALAXIE II A trois volumes",
          "modelYearFrom": "1959-10-01",
          "modelYearTo": "1964-12-01"
        },
        {
          "modelId": 45084,
          "modelName": "GALAXIE II Station Wagon",
          "modelYearFrom": "1959-10-01",
          "modelYearTo": "1964-12-01"
        },
        {
          "modelId": 45085,
          "modelName": "GALAXIE II Hardtop",
          "modelYearFrom": "1963-06-01",
          "modelYearTo": "1964-12-01"
        },
        {
          "modelId": 45086,
          "modelName": "GALAXIE III A trois volumes",
          "modelYearFrom": "1964-09-01",
          "modelYearTo": "1968-12-01"
        },
        {
          "modelId": 45087,
          "modelName": "GALAXIE III Station Wagon",
          "modelYearFrom": "1964-09-01",
          "modelYearTo": "1968-12-01"
        },
        {
          "modelId": 45088,
          "modelName": "GALAXIE III Hardtop",
          "modelYearFrom": "1964-06-01",
          "modelYearTo": "1968-12-01"
        },
        {
          "modelId": 45089,
          "modelName": "GALAXIE IV A trois volumes",
          "modelYearFrom": "1968-09-01",
          "modelYearTo": "1974-12-01"
        },
        {
          "modelId": 45090,
          "modelName": "GALAXIE IV Station Wagon",
          "modelYearFrom": "1968-09-01",
          "modelYearTo": "1974-12-01"
        }
      ]
    },
    {
      "manufacturerId": 1496,
      "manufacturerName": "FORD AUSTRALIA",
      "groupKey": "GT",
      "displayName": "GT",
      "confidence": "rule",
      "models": [
        {
          "modelId": 8211,
          "modelName": "GT Coupé",
          "modelYearFrom": "2003-06-01",
          "modelYearTo": null
        }
      ]
    },
    {
      "manufacturerId": 1496,
      "manufacturerName": "FORD AUSTRALIA",
      "groupKey": "KA",
      "displayName": "KA",
      "confidence": "rule",
      "models": [
        {
          "modelId": 8188,
          "modelName": "KA Berline bicorps trois ou cinq portes (TA, TB)",
          "modelYearFrom": "1999-11-01",
          "modelYearTo": "2003-12-01"
        }
      ]
    },
    {
      "manufacturerId": 1496,
      "manufacturerName": "FORD AUSTRALIA",
      "groupKey": "KUGA",
      "displayName": "KUGA",
      "confidence": "rule",
      "models": [
        {
          "modelId": 11166,
          "modelName": "KUGA (TE)",
          "modelYearFrom": "2011-01-01",
          "modelYearTo": "2014-11-01"
        },
        {
          "modelId": 13807,
          "modelName": "KUGA (TF)",
          "modelYearFrom": "2013-04-01",
          "modelYearTo": "2016-08-01"
        }
      ]
    },
    {
      "manufacturerId": 1496,
      "manufacturerName": "FORD AUSTRALIA",
      "groupKey": "LANDAU",
      "displayName": "LANDAU",
      "confidence": "rule",
      "models": [
        {
          "modelId": 45072,
          "modelName": "LANDAU Coupé (P5)",
          "modelYearFrom": "1973-11-01",
          "modelYearTo": "1976-05-01"
        }
      ]
    },
    {
      "manufacturerId": 1496,
      "manufacturerName": "FORD AUSTRALIA",
      "groupKey": "LASER",
      "displayName": "LASER",
      "confidence": "rule",
      "models": [
        {
          "modelId": 8367,
          "modelName": "LASER Berline bicorps trois ou cinq portes (KA)",
          "modelYearFrom": "1981-03-01",
          "modelYearTo": "1983-02-01"
        },
        {
          "modelId": 8369,
          "modelName": "LASER Berline bicorps trois ou cinq portes (KB)",
          "modelYearFrom": "1983-03-01",
          "modelYearTo": "1985-12-01"
        },
        {
          "modelId": 8371,
          "modelName": "LASER Berline bicorps trois ou cinq portes (KC)",
          "modelYearFrom": "1985-10-01",
          "modelYearTo": "1987-09-01"
        },
        {
          "modelId": 8372,
          "modelName": "LASER A trois volumes (KE)",
          "modelYearFrom": "1987-10-01",
          "modelYearTo": "1990-04-01"
        },
        {
          "modelId": 8373,
          "modelName": "LASER Berline bicorps trois ou cinq portes (KE)",
          "modelYearFrom": "1987-10-01",
          "modelYearTo": "1990-04-01"
        },
        {
          "modelId": 8374,
          "modelName": "LASER A trois volumes (KF)",
          "modelYearFrom": "1990-03-01",
          "modelYearTo": "1991-09-01"
        },
        {
          "modelId": 8439,
          "modelName": "LASER Berline bicorps trois ou cinq portes (KA)",
          "modelYearFrom": "1981-03-01",
          "modelYearTo": "1983-02-01"
        },
        {
          "modelId": 8440,
          "modelName": "LASER Break (KE)",
          "modelYearFrom": "1987-03-01",
          "modelYearTo": "1994-12-01"
        },
        {
          "modelId": 8441,
          "modelName": "LASER Berline bicorps trois ou cinq portes (KF)",
          "modelYearFrom": "1990-03-01",
          "modelYearTo": "1991-09-01"
        },
        {
          "modelId": 8443,
          "modelName": "LASER Berline bicorps trois ou cinq portes (KH)",
          "modelYearFrom": "1991-10-01",
          "modelYearTo": "1994-10-01"
        },
        {
          "modelId": 8444,
          "modelName": "LASER A trois volumes (KH)",
          "modelYearFrom": "1991-03-01",
          "modelYearTo": "1994-10-01"
        },
        {
          "modelId": 8446,
          "modelName": "LASER Berline bicorps trois ou cinq portes (KJ, KL)",
          "modelYearFrom": "1994-10-01",
          "modelYearTo": "1999-03-01"
        },
        {
          "modelId": 8447,
          "modelName": "LASER A trois volumes (KJ, KL)",
          "modelYearFrom": "1994-10-01",
          "modelYearTo": "1999-03-01"
        },
        {
          "modelId": 8448,
          "modelName": "LASER Berline bicorps trois ou cinq portes (KN)",
          "modelYearFrom": "1999-02-01",
          "modelYearTo": "2001-04-01"
        },
        {
          "modelId": 8450,
          "modelName": "LASER A trois volumes (KN)",
          "modelYearFrom": "1999-02-01",
          "modelYearTo": "2001-04-01"
        },
        {
          "modelId": 8451,
          "modelName": "LASER Berline bicorps trois ou cinq portes (KQ, KN III)",
          "modelYearFrom": "2001-03-01",
          "modelYearTo": "2002-09-01"
        },
        {
          "modelId": 8452,
          "modelName": "LASER A trois volumes (KQ)",
          "modelYearFrom": "2001-03-01",
          "modelYearTo": "2002-09-01"
        }
      ]
    },
    {
      "manufacturerId": 1496,
      "manufacturerName": "FORD AUSTRALIA",
      "groupKey": "LTD",
      "displayName": "LTD",
      "confidence": "rule",
      "models": [
        {
          "modelId": 7790,
          "modelName": "LTD A trois volumes (P5)",
          "modelYearFrom": "1973-11-01",
          "modelYearTo": "1976-05-01"
        },
        {
          "modelId": 7791,
          "modelName": "LTD A trois volumes (AU)",
          "modelYearFrom": "1999-06-01",
          "modelYearTo": "2002-12-01"
        },
        {
          "modelId": 7792,
          "modelName": "LTD A trois volumes (BA)",
          "modelYearFrom": "2003-07-01",
          "modelYearTo": "2005-09-01"
        },
        {
          "modelId": 7793,
          "modelName": "LTD A trois volumes (BF)",
          "modelYearFrom": "2005-10-01",
          "modelYearTo": "2007-12-01"
        },
        {
          "modelId": 7794,
          "modelName": "LTD A trois volumes (DA)",
          "modelYearFrom": "1988-06-01",
          "modelYearTo": "1991-06-01"
        },
        {
          "modelId": 7795,
          "modelName": "LTD A trois volumes (DC)",
          "modelYearFrom": "1991-07-01",
          "modelYearTo": "1995-03-01"
        },
        {
          "modelId": 7796,
          "modelName": "LTD A trois volumes (DF)",
          "modelYearFrom": "1995-03-01",
          "modelYearTo": "1996-09-01"
        },
        {
          "modelId": 7797,
          "modelName": "LTD A trois volumes (DL)",
          "modelYearFrom": "1996-09-01",
          "modelYearTo": "1999-06-01"
        },
        {
          "modelId": 7798,
          "modelName": "LTD A trois volumes (FC)",
          "modelYearFrom": "1979-06-01",
          "modelYearTo": "1982-02-01"
        },
        {
          "modelId": 7799,
          "modelName": "LTD A trois volumes (FD)",
          "modelYearFrom": "1982-03-01",
          "modelYearTo": "1984-09-01"
        },
        {
          "modelId": 7800,
          "modelName": "LTD A trois volumes (FE)",
          "modelYearFrom": "1984-10-01",
          "modelYearTo": "1988-10-01"
        }
      ]
    },
    {
      "manufacturerId": 1496,
      "manufacturerName": "FORD AUSTRALIA",
      "groupKey": "MAVERICK",
      "displayName": "MAVERICK",
      "confidence": "rule",
      "models": [
        {
          "modelId": 8454,
          "modelName": "MAVERICK Véhicule tout terrain fermé (DA)",
          "modelYearFrom": "1988-02-01",
          "modelYearTo": "1994-03-01"
        },
        {
          "modelId": 8455,
          "modelName": "MAVERICK Pick-up (DA)",
          "modelYearFrom": "1988-02-01",
          "modelYearTo": "1994-03-01"
        },
        {
          "modelId": 8456,
          "modelName": "MAVERICK Camion plate-forme/Châssis (DA)",
          "modelYearFrom": "1988-02-01",
          "modelYearTo": "1994-03-01"
        }
      ]
    },
    {
      "manufacturerId": 1496,
      "manufacturerName": "FORD AUSTRALIA",
      "groupKey": "METEOR",
      "displayName": "METEOR",
      "confidence": "rule",
      "models": [
        {
          "modelId": 8458,
          "modelName": "METEOR A trois volumes (GA, GB)",
          "modelYearFrom": "1982-04-01",
          "modelYearTo": "1985-09-01"
        },
        {
          "modelId": 8459,
          "modelName": "METEOR Break (GC)",
          "modelYearFrom": "1986-03-01",
          "modelYearTo": "1987-09-01"
        },
        {
          "modelId": 8460,
          "modelName": "METEOR A trois volumes (GC)",
          "modelYearFrom": "1985-10-01",
          "modelYearTo": "1987-09-01"
        }
      ]
    },
    {
      "manufacturerId": 1496,
      "manufacturerName": "FORD AUSTRALIA",
      "groupKey": "MONDEO",
      "displayName": "MONDEO",
      "confidence": "rule",
      "models": [
        {
          "modelId": 8189,
          "modelName": "MONDEO Berline bicorps trois ou cinq portes (HA, HB, HC, HD)",
          "modelYearFrom": "1995-07-01",
          "modelYearTo": "2000-11-01"
        },
        {
          "modelId": 8199,
          "modelName": "MONDEO A trois volumes (HA, HB, HC, HD)",
          "modelYearFrom": "1995-07-01",
          "modelYearTo": "2000-02-01"
        },
        {
          "modelId": 8208,
          "modelName": "MONDEO A trois volumes (HE)",
          "modelYearFrom": "2000-02-01",
          "modelYearTo": "2001-04-01"
        },
        {
          "modelId": 8209,
          "modelName": "MONDEO Berline bicorps trois ou cinq portes (HE)",
          "modelYearFrom": "2000-02-01",
          "modelYearTo": "2001-04-01"
        },
        {
          "modelId": 8282,
          "modelName": "MONDEO A trois volumes (MA, MB)",
          "modelYearFrom": "2007-03-01",
          "modelYearTo": "2015-01-01"
        },
        {
          "modelId": 8283,
          "modelName": "MONDEO Berline bicorps trois ou cinq portes (MA, MB, MC)",
          "modelYearFrom": "2007-03-01",
          "modelYearTo": null
        },
        {
          "modelId": 8284,
          "modelName": "MONDEO Break (MB, MC)",
          "modelYearFrom": "2009-06-01",
          "modelYearTo": null
        },
        {
          "modelId": 8461,
          "modelName": "MONDEO Break (HB, HC, HA)",
          "modelYearFrom": "1995-07-01",
          "modelYearTo": "1998-12-01"
        },
        {
          "modelId": 13801,
          "modelName": "MONDEO Berline bicorps trois ou cinq portes (MD)",
          "modelYearFrom": "2014-09-01",
          "modelYearTo": null
        },
        {
          "modelId": 13802,
          "modelName": "MONDEO Break (MD)",
          "modelYearFrom": "2014-09-01",
          "modelYearTo": null
        }
      ]
    },
    {
      "manufacturerId": 1496,
      "manufacturerName": "FORD AUSTRALIA",
      "groupKey": "MUSTANG",
      "displayName": "MUSTANG",
      "confidence": "rule",
      "models": [
        {
          "modelId": 8191,
          "modelName": "MUSTANG Coupé",
          "modelYearFrom": "1993-09-01",
          "modelYearTo": "2003-09-01"
        },
        {
          "modelId": 8192,
          "modelName": "MUSTANG Décapotable",
          "modelYearFrom": "1993-09-01",
          "modelYearTo": "1999-07-01"
        },
        {
          "modelId": 8217,
          "modelName": "MUSTANG Coupé",
          "modelYearFrom": "2004-09-01",
          "modelYearTo": "2014-07-01"
        },
        {
          "modelId": 8218,
          "modelName": "MUSTANG Décapotable",
          "modelYearFrom": "2004-09-01",
          "modelYearTo": "2014-07-01"
        },
        {
          "modelId": 13372,
          "modelName": "MUSTANG Décapotable (FM, FN)",
          "modelYearFrom": "2014-12-01",
          "modelYearTo": "2023-11-01"
        },
        {
          "modelId": 13373,
          "modelName": "MUSTANG Coupé (FM, FN)",
          "modelYearFrom": "2014-12-01",
          "modelYearTo": "2023-11-01"
        },
        {
          "modelId": 44712,
          "modelName": "MUSTANG MACH-E (CGW)",
          "modelYearFrom": "2020-07-01",
          "modelYearTo": null
        },
        {
          "modelId": 45160,
          "modelName": "MUSTANG Coupé (FO)",
          "modelYearFrom": "2023-12-01",
          "modelYearTo": null
        },
        {
          "modelId": 45161,
          "modelName": "MUSTANG Décapotable (FO)",
          "modelYearFrom": "2023-12-01",
          "modelYearTo": null
        }
      ]
    },
    {
      "manufacturerId": 1496,
      "manufacturerName": "FORD AUSTRALIA",
      "groupKey": "PREFECT",
      "displayName": "PREFECT",
      "confidence": "rule",
      "models": [
        {
          "modelId": 45585,
          "modelName": "PREFECT A trois volumes (E93A)",
          "modelYearFrom": "1938-10-01",
          "modelYearTo": "1949-09-01"
        },
        {
          "modelId": 45586,
          "modelName": "PREFECT Coupé (E93A)",
          "modelYearFrom": "1938-10-01",
          "modelYearTo": "1949-09-01"
        },
        {
          "modelId": 45587,
          "modelName": "PREFECT Décapotable (E93A)",
          "modelYearFrom": "1938-10-01",
          "modelYearTo": "1949-09-01"
        },
        {
          "modelId": 45588,
          "modelName": "PREFECT Fourgon/Break (E93A)",
          "modelYearFrom": "1938-10-01",
          "modelYearTo": "1949-09-01"
        },
        {
          "modelId": 45589,
          "modelName": "PREFECT Pick-up (E93A)",
          "modelYearFrom": "1938-10-01",
          "modelYearTo": "1949-09-01"
        },
        {
          "modelId": 45591,
          "modelName": "PREFECT A trois volumes (E03A)",
          "modelYearFrom": "1939-10-01",
          "modelYearTo": "1945-09-01"
        },
        {
          "modelId": 45592,
          "modelName": "PREFECT Coupé (E03A)",
          "modelYearFrom": "1939-10-01",
          "modelYearTo": "1945-09-01"
        },
        {
          "modelId": 45593,
          "modelName": "PREFECT Décapotable (E03A)",
          "modelYearFrom": "1939-10-01",
          "modelYearTo": "1945-09-01"
        },
        {
          "modelId": 45594,
          "modelName": "PREFECT Fourgon/Break (E03A)",
          "modelYearFrom": "1939-10-01",
          "modelYearTo": "1945-09-01"
        },
        {
          "modelId": 45595,
          "modelName": "PREFECT Pick-up (E03A)",
          "modelYearFrom": "1939-10-01",
          "modelYearTo": "1945-09-01"
        },
        {
          "modelId": 45596,
          "modelName": "PREFECT A trois volumes (E53A)",
          "modelYearFrom": "1945-10-01",
          "modelYearTo": "1948-09-01"
        },
        {
          "modelId": 45597,
          "modelName": "PREFECT Fourgon/Break (E53A)",
          "modelYearFrom": "1945-10-01",
          "modelYearTo": "1948-09-01"
        },
        {
          "modelId": 45598,
          "modelName": "PREFECT Pick-up (E53A)",
          "modelYearFrom": "1945-10-01",
          "modelYearTo": "1948-09-01"
        },
        {
          "modelId": 45599,
          "modelName": "PREFECT A trois volumes (E493A)",
          "modelYearFrom": "1949-10-01",
          "modelYearTo": "1953-09-01"
        },
        {
          "modelId": 45600,
          "modelName": "PREFECT A trois volumes (A493A)",
          "modelYearFrom": "1949-10-01",
          "modelYearTo": "1953-09-01"
        },
        {
          "modelId": 45601,
          "modelName": "PREFECT Pick-up (A493A)",
          "modelYearFrom": "1949-10-01",
          "modelYearTo": "1953-09-01"
        },
        {
          "modelId": 45602,
          "modelName": "PREFECT A trois volumes (100E)",
          "modelYearFrom": "1952-10-01",
          "modelYearTo": "1959-09-01"
        },
        {
          "modelId": 45603,
          "modelName": "PREFECT A trois volumes (107E)",
          "modelYearFrom": "1959-10-01",
          "modelYearTo": "1962-04-01"
        }
      ]
    },
    {
      "manufacturerId": 1496,
      "manufacturerName": "FORD AUSTRALIA",
      "groupKey": "PROBE",
      "displayName": "PROBE",
      "confidence": "rule",
      "models": [
        {
          "modelId": 8194,
          "modelName": "PROBE (ST, SU, SV)",
          "modelYearFrom": "1994-07-01",
          "modelYearTo": "1998-01-01"
        }
      ]
    },
    {
      "manufacturerId": 1496,
      "manufacturerName": "FORD AUSTRALIA",
      "groupKey": "PUMA",
      "displayName": "PUMA",
      "confidence": "rule",
      "models": [
        {
          "modelId": 41803,
          "modelName": "PUMA (JK)",
          "modelYearFrom": "2020-07-01",
          "modelYearTo": null
        }
      ]
    },
    {
      "manufacturerId": 1496,
      "manufacturerName": "FORD AUSTRALIA",
      "groupKey": "RAIDER",
      "displayName": "RAIDER",
      "confidence": "rule",
      "models": [
        {
          "modelId": 8462,
          "modelName": "RAIDER Véhicule tout terrain fermé (UV)",
          "modelYearFrom": "1991-08-01",
          "modelYearTo": "1997-07-01"
        }
      ]
    },
    {
      "manufacturerId": 1496,
      "manufacturerName": "FORD AUSTRALIA",
      "groupKey": "RANGER",
      "displayName": "RANGER",
      "confidence": "rule",
      "models": [
        {
          "modelId": 8203,
          "modelName": "RANGER Pick-up (PJ)",
          "modelYearFrom": "2006-11-01",
          "modelYearTo": "2009-03-01"
        },
        {
          "modelId": 8463,
          "modelName": "RANGER Camion plate-forme/Châssis (PJ)",
          "modelYearFrom": "2006-11-01",
          "modelYearTo": "2009-03-01"
        },
        {
          "modelId": 8464,
          "modelName": "RANGER Pick-up (PK)",
          "modelYearFrom": "2009-03-01",
          "modelYearTo": "2011-11-01"
        },
        {
          "modelId": 8465,
          "modelName": "RANGER Camion plate-forme/Châssis (PK)",
          "modelYearFrom": "2009-03-01",
          "modelYearTo": "2011-11-01"
        },
        {
          "modelId": 9756,
          "modelName": "RANGER Pick-up (PX)",
          "modelYearFrom": "2011-04-01",
          "modelYearTo": "2022-05-01"
        },
        {
          "modelId": 9757,
          "modelName": "RANGER Camion plate-forme/Châssis (PX)",
          "modelYearFrom": "2011-11-01",
          "modelYearTo": "2022-05-01"
        },
        {
          "modelId": 43079,
          "modelName": "RANGER Pick-up (PY)",
          "modelYearFrom": "2022-06-01",
          "modelYearTo": null
        },
        {
          "modelId": 43080,
          "modelName": "RANGER Camion plate-forme/Châssis (PY)",
          "modelYearFrom": "2022-06-01",
          "modelYearTo": null
        }
      ]
    },
    {
      "manufacturerId": 1496,
      "manufacturerName": "FORD AUSTRALIA",
      "groupKey": "SPECTRON",
      "displayName": "SPECTRON",
      "confidence": "rule",
      "models": [
        {
          "modelId": 8466,
          "modelName": "SPECTRON Autobus/Autocar",
          "modelYearFrom": "1983-01-01",
          "modelYearTo": "1990-04-01"
        }
      ]
    },
    {
      "manufacturerId": 1496,
      "manufacturerName": "FORD AUSTRALIA",
      "groupKey": "TAURUS",
      "displayName": "TAURUS",
      "confidence": "rule",
      "models": [
        {
          "modelId": 8468,
          "modelName": "TAURUS A trois volumes (DN, DP)",
          "modelYearFrom": "1996-03-01",
          "modelYearTo": "1998-09-01"
        }
      ]
    },
    {
      "manufacturerId": 1496,
      "manufacturerName": "FORD AUSTRALIA",
      "groupKey": "TELSTAR",
      "displayName": "TELSTAR",
      "confidence": "rule",
      "models": [
        {
          "modelId": 8243,
          "modelName": "TELSTAR Berline bicorps trois ou cinq portes (AT)",
          "modelYearFrom": "1987-11-01",
          "modelYearTo": "1989-09-01"
        },
        {
          "modelId": 8244,
          "modelName": "TELSTAR A trois volumes (AT)",
          "modelYearFrom": "1987-11-01",
          "modelYearTo": "1991-07-01"
        },
        {
          "modelId": 8245,
          "modelName": "TELSTAR Berline bicorps trois ou cinq portes (AX)",
          "modelYearFrom": "1992-01-01",
          "modelYearTo": "1994-08-01"
        },
        {
          "modelId": 8246,
          "modelName": "TELSTAR A trois volumes (AX)",
          "modelYearFrom": "1992-01-01",
          "modelYearTo": "1996-08-01"
        },
        {
          "modelId": 8471,
          "modelName": "TELSTAR Berline bicorps trois ou cinq portes (AR)",
          "modelYearFrom": "1983-05-01",
          "modelYearTo": "1985-08-01"
        },
        {
          "modelId": 8472,
          "modelName": "TELSTAR A trois volumes (AR)",
          "modelYearFrom": "1983-05-01",
          "modelYearTo": "1985-08-01"
        },
        {
          "modelId": 8473,
          "modelName": "TELSTAR Berline bicorps trois ou cinq portes (AS)",
          "modelYearFrom": "1985-09-01",
          "modelYearTo": "1987-10-01"
        },
        {
          "modelId": 8474,
          "modelName": "TELSTAR A trois volumes (AS)",
          "modelYearFrom": "1985-09-01",
          "modelYearTo": "1987-10-01"
        },
        {
          "modelId": 8475,
          "modelName": "TELSTAR Berline bicorps trois ou cinq portes (AV)",
          "modelYearFrom": "1990-01-01",
          "modelYearTo": "1992-01-01"
        },
        {
          "modelId": 8476,
          "modelName": "TELSTAR Berline bicorps trois ou cinq portes (AY)",
          "modelYearFrom": "1994-10-01",
          "modelYearTo": "1996-11-01"
        },
        {
          "modelId": 8477,
          "modelName": "TELSTAR A trois volumes (AY)",
          "modelYearFrom": "1994-05-01",
          "modelYearTo": "1997-06-01"
        }
      ]
    },
    {
      "manufacturerId": 1496,
      "manufacturerName": "FORD AUSTRALIA",
      "groupKey": "TERRITORY",
      "displayName": "TERRITORY",
      "confidence": "rule",
      "models": [
        {
          "modelId": 7801,
          "modelName": "TERRITORY (SX, SY)",
          "modelYearFrom": "2004-05-01",
          "modelYearTo": "2011-05-01"
        },
        {
          "modelId": 9760,
          "modelName": "TERRITORY (SZ)",
          "modelYearFrom": "2011-05-01",
          "modelYearTo": null
        }
      ]
    },
    {
      "manufacturerId": 1496,
      "manufacturerName": "FORD AUSTRALIA",
      "groupKey": "TICKFORD",
      "displayName": "TICKFORD",
      "confidence": "rule",
      "models": [
        {
          "modelId": 7947,
          "modelName": "TICKFORD TE 50 A trois volumes (AU)",
          "modelYearFrom": "1999-10-01",
          "modelYearTo": null
        },
        {
          "modelId": 7948,
          "modelName": "TICKFORD TL 50 A trois volumes (AU)",
          "modelYearFrom": "1999-10-01",
          "modelYearTo": "2002-12-01"
        },
        {
          "modelId": 7949,
          "modelName": "TICKFORD TS 50 A trois volumes (AU)",
          "modelYearFrom": "1999-10-01",
          "modelYearTo": "2002-12-01"
        }
      ]
    },
    {
      "manufacturerId": 1496,
      "manufacturerName": "FORD AUSTRALIA",
      "groupKey": "TOURNEO",
      "displayName": "TOURNEO",
      "confidence": "rule",
      "models": [
        {
          "modelId": 13817,
          "modelName": "TOURNEO CUSTOM Autobus/Autocar",
          "modelYearFrom": "2014-05-01",
          "modelYearTo": null
        }
      ]
    },
    {
      "manufacturerId": 1496,
      "manufacturerName": "FORD AUSTRALIA",
      "groupKey": "TRANSIT",
      "displayName": "TRANSIT",
      "confidence": "rule",
      "models": [
        {
          "modelId": 8187,
          "modelName": "TRANSIT Autobus/Autocar (VF, VG)",
          "modelYearFrom": "1994-06-01",
          "modelYearTo": "2000-06-01"
        },
        {
          "modelId": 8197,
          "modelName": "TRANSIT Camion plate-forme/Châssis (VF, VG)",
          "modelYearFrom": "1991-09-01",
          "modelYearTo": "1994-08-01"
        },
        {
          "modelId": 8198,
          "modelName": "TRANSIT Camion plate-forme/Châssis (VF, VG)",
          "modelYearFrom": "1994-08-01",
          "modelYearTo": "2000-12-01"
        },
        {
          "modelId": 8204,
          "modelName": "TRANSIT Autobus/Autocar (VH, VJ)",
          "modelYearFrom": "2000-01-01",
          "modelYearTo": "2006-12-01"
        },
        {
          "modelId": 8205,
          "modelName": "TRANSIT Camion plate-forme/Châssis (VH, VJ)",
          "modelYearFrom": "2000-01-01",
          "modelYearTo": "2006-09-01"
        },
        {
          "modelId": 8214,
          "modelName": "TRANSIT Autobus/Autocar (VM)",
          "modelYearFrom": "2006-07-01",
          "modelYearTo": null
        },
        {
          "modelId": 8215,
          "modelName": "TRANSIT Fourgon (VM)",
          "modelYearFrom": "2006-07-01",
          "modelYearTo": null
        },
        {
          "modelId": 8216,
          "modelName": "TRANSIT Camion plate-forme/Châssis (VM)",
          "modelYearFrom": "2006-07-01",
          "modelYearTo": null
        },
        {
          "modelId": 8479,
          "modelName": "TRANSIT MK 2 Autobus/Autocar (125)",
          "modelYearFrom": "1978-03-01",
          "modelYearTo": "1983-12-01"
        },
        {
          "modelId": 8480,
          "modelName": "TRANSIT MK 2 Fourgon (125, 175)",
          "modelYearFrom": "1978-03-01",
          "modelYearTo": "1983-12-01"
        },
        {
          "modelId": 8487,
          "modelName": "TRANSIT Fourgon (VF, VG, VE)",
          "modelYearFrom": "1994-06-01",
          "modelYearTo": "2000-12-01"
        },
        {
          "modelId": 8488,
          "modelName": "TRANSIT Fourgon (VH, VJ)",
          "modelYearFrom": "2000-01-01",
          "modelYearTo": "2006-12-01"
        },
        {
          "modelId": 13231,
          "modelName": "TRANSIT Fourgon (VO)",
          "modelYearFrom": "2014-09-01",
          "modelYearTo": null
        },
        {
          "modelId": 13232,
          "modelName": "TRANSIT Camion plate-forme/Châssis (VO)",
          "modelYearFrom": "2014-09-01",
          "modelYearTo": null
        },
        {
          "modelId": 13813,
          "modelName": "TRANSIT CUSTOM Fourgon (VN)",
          "modelYearFrom": "2013-09-01",
          "modelYearTo": "2023-07-01"
        },
        {
          "modelId": 39862,
          "modelName": "TRANSIT MK 1 Fourgon (100, 115, 150)",
          "modelYearFrom": "1965-10-01",
          "modelYearTo": "1978-03-01"
        },
        {
          "modelId": 41342,
          "modelName": "TRANSIT Autobus/Autocar (VO)",
          "modelYearFrom": "2014-09-01",
          "modelYearTo": null
        },
        {
          "modelId": 44655,
          "modelName": "TRANSIT MK 1 Autobus/Autocar (115)",
          "modelYearFrom": "1965-10-01",
          "modelYearTo": "1978-03-01"
        },
        {
          "modelId": 44656,
          "modelName": "TRANSIT MK 1 Camion plate-forme/Châssis (100, 150, 175)",
          "modelYearFrom": "1965-10-01",
          "modelYearTo": "1978-03-01"
        },
        {
          "modelId": 45159,
          "modelName": "TRANSIT CUSTOM Fourgon (AV)",
          "modelYearFrom": "2023-08-01",
          "modelYearTo": null
        }
      ]
    },
    {
      "manufacturerId": 1496,
      "manufacturerName": "FORD AUSTRALIA",
      "groupKey": "ZEPHYR",
      "displayName": "ZEPHYR",
      "confidence": "rule",
      "models": [
        {
          "modelId": 45849,
          "modelName": "ZEPHYR SIX A trois volumes (EOTTA)",
          "modelYearFrom": "1953-01-01",
          "modelYearTo": "1956-01-01"
        },
        {
          "modelId": 45850,
          "modelName": "ZEPHYR SIX Décapotable (EOTTA)",
          "modelYearFrom": "1953-01-01",
          "modelYearTo": "1956-01-01"
        },
        {
          "modelId": 45851,
          "modelName": "ZEPHYR SIX A trois volumes (206E)",
          "modelYearFrom": "1956-02-01",
          "modelYearTo": "1962-03-01"
        },
        {
          "modelId": 45852,
          "modelName": "ZEPHYR SIX Break (206E)",
          "modelYearFrom": "1956-02-01",
          "modelYearTo": "1962-03-01"
        },
        {
          "modelId": 45853,
          "modelName": "ZEPHYR SIX Décapotable (206E)",
          "modelYearFrom": "1956-02-01",
          "modelYearTo": "1962-03-01"
        },
        {
          "modelId": 45854,
          "modelName": "ZEPHYR SIX Coupe Utility (206E)",
          "modelYearFrom": "1956-02-01",
          "modelYearTo": "1962-03-01"
        },
        {
          "modelId": 45855,
          "modelName": "ZEPHYR SIX A trois volumes (213E)",
          "modelYearFrom": "1962-04-01",
          "modelYearTo": "1965-12-01"
        }
      ]
    }
  ]
}