{
  "totalResults": 1,
  "hasNextPage": false,
  "requestProcessingTime": 0,
  "products": [
    {
      "sku": "262007",
      "index": "LPR01840",
      "tecDoc": "01840",
      "tecDocProd": "197",
      "articleNumber": "01840",
      "brand": "LPR",
      "shortDescription": "Brake Shoe Set, parking brake",
      "description": "Brake shoe fits: MERCEDES /8 (W114), /8 (W115), 123 (C123), 123 (W123), 123 T-MODEL (S123), CABRIOLET (W111, W112), COUPE (W111, W112), HECKFLOSSE (W110), HECKFLOSSE (W111 1.9-6.8 07.53-06.91",
      "gtuCode": "GTU_07",
      "eans": [
        "5900427066403"
      ],
      "packageWeight": "0,916",
      "packageWidth": "12,000",
      "packageDepth": "7,000",
      "packageHeight": "21,000",
      "customsCode": "87083099",
      "blockedReturn": false,
      "genericArticleReferences": [
        {
          "genericArticleId": "GenericArticle_1419",
          "primary": true,
          "name": {
            "en": "Brake Shoe Set, parking brake"
          }
        }
      ]
    }
  ]
}