{
  "totalResults": 1,
  "hasNextPage": false,
  "requestProcessingTime": 0,
  "products": [
    {
      "sku": "291719",
      "index": "HP107 398",
      "tecDoc": "107 398",
      "tecDocProd": "301",
      "articleNumber": "107 398",
      "brand": "HANS PRIES",
      "shortDescription": "Speedometer cable",
      "description": "Speedometer cable drive fits: SEAT ALHAMBRA, VW SHARAN, TRANSPORTER T4 1.8-2.8 07.90-03.10",
      "eans": [
        "4063926529341"
      ],
      "packageWeight": "0,009",
      "packageWidth": "1,500",
      "packageDepth": "9,800",
      "packageHeight": "1,500",
      "customsCode": "90299000",
      "blockedReturn": false,
      "genericArticleReferences": [
        {
          "genericArticleId": "GenericArticle_2202",
          "primary": false,
          "name": {
            "en": "Angle Drive, speedometer cable"
          }
        },
        {
          "genericArticleId": "GenericArticle_1150",
          "primary": true,
          "name": {
            "en": "Speedometer cable"
          }
        }
      ]
    }
  ]
}