{
  "totalResults": 1,
  "hasNextPage": false,
  "requestProcessingTime": 0,
  "products": [
    {
      "sku": "B5283D",
      "index": "8JS003 481-823",
      "tecDoc": "8JS 003 481-823",
      "tecDocProd": "2",
      "articleNumber": "8JS 003 481-823",
      "brand": "HELLA",
      "shortDescription": "Fuse Kit",
      "description": "Fuse (8pcs, rated current: 2,5/10/20/25A, length: 5-6,3-20-32mm) Glass",
      "customsCode": "85361050",
      "blockedReturn": true,
      "genericArticleReferences": [
        {
          "genericArticleId": "GenericArticle_819",
          "primary": true,
          "name": {
            "en": "Fuse Kit"
          }
        }
      ]
    }
  ]
}