{
  "totalResults": 1,
  "hasNextPage": false,
  "requestProcessingTime": 0,
  "products": [
    {
      "sku": "B56440",
      "index": "HP207 476",
      "tecDoc": "207 476",
      "tecDocProd": "301",
      "articleNumber": "207 476",
      "brand": "HANS PRIES",
      "shortDescription": "Rocker arm",
      "description": "Rocker arm fits: ALFA ROMEO 147, 156, GT, FIAT BRAVO II, CROMA, STILO, LANCIA THESIS, OPEL ASTRA H, ASTRA H GTC, ASTRA H/KOMBI, SIGNUM, VECTRA C, VECTRA C GTS, ZAFIRA B 1.9D/2.4D 10.01-04.15",
      "eans": [
        "4063926098991"
      ],
      "customsCode": "84099900",
      "blockedReturn": true,
      "genericArticleReferences": [
        {
          "genericArticleId": "GenericArticle_561",
          "primary": true,
          "name": {
            "en": "Rocker arm"
          }
        }
      ]
    }
  ]
}