{
  "totalResults": 1,
  "hasNextPage": false,
  "requestProcessingTime": 0,
  "products": [
    {
      "sku": "BB37A7",
      "index": "1.18364",
      "tecDoc": "1.18364",
      "tecDocProd": "355",
      "articleNumber": "1.18364",
      "brand": "DT SPARE PARTS",
      "shortDescription": "Oil filter",
      "description": "Oil filter (cartridge) fits: MAN TGS I, SCANIA 2, 3, 3 BUS, 4, 4 BUS, F, G I, G II, IRIZAR PB, K I, L, N BUS, P I, P II, R I, R II, S, T, TOURING D2066LF85-OSC11.03 01.81-",
      "packageWeight": "0,168",
      "packageWidth": "10,000",
      "packageDepth": "15,000",
      "packageHeight": "10,000",
      "customsCode": "84212300",
      "blockedReturn": true,
      "genericArticleReferences": [
        {
          "genericArticleId": "GenericArticle_7",
          "primary": true,
          "name": {
            "en": "Oil filter"
          }
        },
        {
          "genericArticleId": "GenericArticle_3503",
          "primary": false,
          "name": {
            "en": "Oil Filter, retarder"
          }
        }
      ]
    }
  ]
}