{
  "totalResults": 1,
  "hasNextPage": false,
  "requestProcessingTime": 0,
  "products": [
    {
      "sku": "C696E6",
      "index": "70-41369-00",
      "tecDoc": "70-41369-00",
      "tecDocProd": "9",
      "articleNumber": "70-41369-00",
      "brand": "REINZ",
      "shortDescription": "Additive, turbocharger (first fill)",
      "description": "Turbine oil",
      "gtuCode": "GTU_03",
      "eans": [
        "4026635040194"
      ],
      "packageWeight": "0,022",
      "packageWidth": "33,200",
      "packageDepth": "15,500",
      "packageHeight": "29,000",
      "customsCode": "34039900",
      "blockedReturn": true,
      "genericArticleReferences": [
        {
          "genericArticleId": "GenericArticle_4869",
          "primary": true,
          "name": {
            "en": "Additive, turbocharger (first fill)"
          }
        }
      ]
    }
  ]
}