{
  "totalResults": 1,
  "hasNextPage": false,
  "requestProcessingTime": 0,
  "products": [
    {
      "sku": "D465D8",
      "index": "13.8162-0022.1",
      "tecDoc": "13.8162-0022.1",
      "tecDocProd": "3",
      "articleNumber": "13.8162-0022.1",
      "brand": "ATE",
      "shortDescription": "Cover, brake caliper",
      "description": "Brake disc cover L/R (clamp cover)",
      "gtuCode": "GTU_07",
      "eans": [
        "4006633254946"
      ],
      "packageWeight": "0,034",
      "packageWidth": "7,000",
      "packageDepth": "2,500",
      "packageHeight": "10,500",
      "customsCode": "87082990",
      "blockedReturn": true,
      "genericArticleReferences": [
        {
          "genericArticleId": "GenericArticle_2247",
          "primary": true,
          "name": {
            "en": "Cover, brake caliper"
          }
        }
      ]
    }
  ]
}