{
  "totalResults": 1,
  "hasNextPage": false,
  "requestProcessingTime": 0,
  "products": [
    {
      "sku": "DDF61B",
      "index": "F 00B H40 222",
      "tecDoc": "F 00B H40 222",
      "tecDocProd": "30",
      "articleNumber": "F 00B H40 222",
      "brand": "BOSCH",
      "shortDescription": "Injector, urea injection",
      "description": "DeNOx system ammonia injector",
      "eans": [
        "4047025170468"
      ],
      "packageWeight": "0,096",
      "packageWidth": "3,900",
      "packageDepth": "10,300",
      "packageHeight": "10,200",
      "customsCode": "84818059",
      "blockedReturn": true,
      "genericArticleReferences": [
        {
          "genericArticleId": "GenericArticle_4253",
          "primary": true,
          "name": {
            "en": "Injector, urea injection"
          }
        }
      ]
    }
  ]
}