{
  "totalResults": 1,
  "hasNextPage": false,
  "requestProcessingTime": 0,
  "products": [
    {
      "sku": "G051GQ",
      "index": "FE102677",
      "tecDoc": "102677",
      "tecDocProd": "101",
      "articleNumber": "102677",
      "brand": "FEBI",
      "shortDescription": "Air filter",
      "description": "Air filter (Cartridge) fits: MERCEDES V (638/2), VITO (W638) 2.0-2.8 02.96-07.03",
      "customsCode": "84213100",
      "blockedReturn": true,
      "genericArticleReferences": [
        {
          "genericArticleId": "GenericArticle_8",
          "primary": true,
          "name": {
            "en": "Air filter"
          }
        }
      ]
    }
  ]
}