{
  "totalResults": 1,
  "hasNextPage": false,
  "requestProcessingTime": 0,
  "products": [
    {
      "sku": "G0VFYX",
      "index": "MCF190SP",
      "tecDoc": "MCF190SP",
      "tecDocProd": "161",
      "articleNumber": "MCF190SP",
      "brand": "TRW",
      "shortDescription": "Footrest System",
      "description": "Footrest (set)",
      "customsCode": "87141090",
      "blockedReturn": true,
      "genericArticleReferences": [
        {
          "genericArticleId": "GenericArticle_5346",
          "primary": true,
          "name": {
            "en": "Footrest System"
          }
        }
      ]
    }
  ]
}